{"id":153,"from_id":-160197155,"owner_id":-160197155,"date":1522356649,"marked_as_ads":0,"post_type":"post","text":"","copy_history":[{"id":1527,"owner_id":-100321975,"from_id":-100321975,"date":1518097968,"post_type":"post","text":"Возьмемся за руки, поднимайся Россия!\n\nДень становится длиннее, солнышко выше! Мы заходим на новый круг и планируем в июне 2018 г. провести Хоровод Мира в Санкт-Петербурге и еще 100 городах России и мира.\n \nДавайте вместе запустим сигнал \"мира\" всему миру, вставайте в хоровод, создавайте хоровод!\n\nОтправляйте это послание всем, люди ждут этой вести!\n\nВся информация будет размещаться в этой группе, следите за новостями: https://vk.com/horovodrus . Сайт: http://horovod2017.ru/\n\nА пока посмотрите видео о Хороводе Мира, \nкоторый мы вместе создали в прошлом году!","signer_id":1848257,"attachments":[{"type":"video","video":{"id":456239081,"owner_id":-100321975,"title":"Хороводы России на Дворцовой Площади","duration":420,"description":"15 августа 2017","date":1504188943,"comments":48,"views":5376,"photo_130":"https://pp.userapi.com/c639124/u1848257/video/s_f6b686ce.jpg","photo_320":"https://pp.userapi.com/c639124/u1848257/video/l_7039c844.jpg","photo_640":"https://pp.userapi.com/c639124/u1848257/video/y_048d6e14.jpg","access_key":"906ac77b67ca9e0c21","platform":"YouTube","can_add":1}}],"post_source":{"type":"vk"}}],"post_source":{"type":"vk"},"comments":{"count":0,"groups_can_post":true,"can_post":1},"likes":{"count":6,"user_likes":0,"can_like":1,"can_publish":1},"reposts":{"count":2,"user_reposted":0},"views":{"count":183}}