{"id":18,"from_id":-160197155,"owner_id":-160197155,"date":1516487844,"marked_as_ads":0,"post_type":"post","text":"Предлагаем для внимания развивающие беседы передовых людей современности о \"русском мире\", его границах, культуре, генетике","copy_history":[{"id":171634116,"owner_id":49420399,"from_id":49420399,"date":1455446391,"post_type":"video","text":"","attachments":[{"type":"video","video":{"id":171634116,"owner_id":49420399,"title":"Родное Видение - Г. Сидоров ответы на вопросы парня с севера Руси в гостях у В. Говорова","duration":4657,"description":"Родное Видение - Г. Сидоров ответы на вопросы парня с севера Руси в гостях у Владимира Говорова.","date":1455446391,"comments":0,"views":3444,"photo_130":"https://pp.userapi.com/c630822/u212752969/video/s_58d59363.jpg","photo_320":"https://pp.userapi.com/c630822/u212752969/video/l_83d9cd60.jpg","photo_800":"https://pp.userapi.com/c630822/u212752969/video/x_d0fcc29c.jpg","access_key":"47c6481b805ec02d4a","platform":"YouTube","can_add":1}}],"post_source":{"type":"vk"}}],"post_source":{"type":"vk"},"comments":{"count":0,"groups_can_post":true,"can_post":1},"likes":{"count":5,"user_likes":0,"can_like":1,"can_publish":1},"reposts":{"count":1,"user_reposted":0},"views":{"count":260}}